{
  "coingecko_id": "ethena-staked-usde",
  "name": "Ethena Staked USDe",
  "symbol": "SUSDE",
  "charts": {
    "7d": {
      "prices": [
        [
          1747353600000,
          1.1721400562370599
        ],
        [
          1747872000000,
          1.1741113052494505
        ],
        [
          1748390400000,
          1.1749740800085562
        ],
        [
          1748908800000,
          1.1763204094222222
        ],
        [
          1749427200000,
          1.1780295498072166
        ],
        [
          1749945600000,
          1.1770929192937263
        ],
        [
          1750464000000,
          1.1773177199968636
        ],
        [
          1750982400000,
          1.177426881293148
        ],
        [
          1751500800000,
          1.177976654454332
        ],
        [
          1752019200000,
          1.1789545591921833
        ],
        [
          1752537600000,
          1.180953473686915
        ],
        [
          1753056000000,
          1.1844503149397274
        ],
        [
          1753574400000,
          1.1858470702031463
        ],
        [
          1754092800000,
          1.18524471320461
        ],
        [
          1754611200000,
          1.1877257888175907
        ],
        [
          1755129600000,
          1.1871351457557482
        ],
        [
          1755648000000,
          1.1881656285751754
        ],
        [
          1756166400000,
          1.1917454637113325
        ],
        [
          1756684800000,
          1.1923586488422062
        ],
        [
          1757203200000,
          1.1962448914882338
        ],
        [
          1757721600000,
          1.197273762814302
        ],
        [
          1758240000000,
          1.198384831301199
        ],
        [
          1758758400000,
          1.1960405818664699
        ],
        [
          1759276800000,
          1.1986318596307763
        ],
        [
          1759795200000,
          1.1989399267290775
        ],
        [
          1760313600000,
          1.200090717090151
        ],
        [
          1760832000000,
          1.2001746521201018
        ],
        [
          1761350400000,
          1.201874430971646
        ]
      ],
      "prices_percent_change": [
        [
          1747353600000,
          0
        ],
        [
          1747872000000,
          0.17
        ],
        [
          1748390400000,
          0.24
        ],
        [
          1748908800000,
          0.36
        ],
        [
          1749427200000,
          0.5
        ],
        [
          1749945600000,
          0.42
        ],
        [
          1750464000000,
          0.44
        ],
        [
          1750982400000,
          0.45
        ],
        [
          1751500800000,
          0.5
        ],
        [
          1752019200000,
          0.58
        ],
        [
          1752537600000,
          0.75
        ],
        [
          1753056000000,
          1.05
        ],
        [
          1753574400000,
          1.17
        ],
        [
          1754092800000,
          1.12
        ],
        [
          1754611200000,
          1.33
        ],
        [
          1755129600000,
          1.28
        ],
        [
          1755648000000,
          1.37
        ],
        [
          1756166400000,
          1.67
        ],
        [
          1756684800000,
          1.72
        ],
        [
          1757203200000,
          2.06
        ],
        [
          1757721600000,
          2.14
        ],
        [
          1758240000000,
          2.24
        ],
        [
          1758758400000,
          2.04
        ],
        [
          1759276800000,
          2.26
        ],
        [
          1759795200000,
          2.29
        ],
        [
          1760313600000,
          2.38
        ],
        [
          1760832000000,
          2.39
        ],
        [
          1761350400000,
          2.54
        ]
      ],
      "market_caps": [
        [
          1747353600000,
          2183977244.623726
        ],
        [
          1747872000000,
          2503764923.4979143
        ],
        [
          1748390400000,
          2669308293.195483
        ],
        [
          1748908800000,
          3272995732.783645
        ],
        [
          1749427200000,
          3454869925.028943
        ],
        [
          1749945600000,
          3496041181.445848
        ],
        [
          1750464000000,
          3186648933.067603
        ],
        [
          1750982400000,
          3173116563.210682
        ],
        [
          1751500800000,
          3147391009.381725
        ],
        [
          1752019200000,
          3123227434.5095267
        ],
        [
          1752537600000,
          3121901472.499247
        ],
        [
          1753056000000,
          3615361252.122268
        ],
        [
          1753574400000,
          4167564154.4659424
        ],
        [
          1754092800000,
          5019218381.761251
        ],
        [
          1754611200000,
          5021820740.036101
        ],
        [
          1755129600000,
          5494879824.235885
        ],
        [
          1755648000000,
          5543058094.526718
        ],
        [
          1756166400000,
          5590729359.500165
        ],
        [
          1756684800000,
          5633025852.94286
        ],
        [
          1757203200000,
          5716155042.719011
        ],
        [
          1757721600000,
          5802514551.918153
        ],
        [
          1758240000000,
          6051292947.688032
        ],
        [
          1758758400000,
          6057065107.284272
        ],
        [
          1759276800000,
          6015093370.322746
        ],
        [
          1759795200000,
          5830589152.734708
        ],
        [
          1760313600000,
          5726598889.196707
        ],
        [
          1760832000000,
          5577673942.9918165
        ],
        [
          1761350400000,
          5150010372.370932
        ]
      ],
      "market_caps_percent_change": [
        [
          1747353600000,
          0
        ],
        [
          1747872000000,
          14.64
        ],
        [
          1748390400000,
          22.22
        ],
        [
          1748908800000,
          49.86
        ],
        [
          1749427200000,
          58.19
        ],
        [
          1749945600000,
          60.08
        ],
        [
          1750464000000,
          45.91
        ],
        [
          1750982400000,
          45.29
        ],
        [
          1751500800000,
          44.11
        ],
        [
          1752019200000,
          43.01
        ],
        [
          1752537600000,
          42.95
        ],
        [
          1753056000000,
          65.54
        ],
        [
          1753574400000,
          90.82
        ],
        [
          1754092800000,
          129.82
        ],
        [
          1754611200000,
          129.94
        ],
        [
          1755129600000,
          151.6
        ],
        [
          1755648000000,
          153.81
        ],
        [
          1756166400000,
          155.99
        ],
        [
          1756684800000,
          157.93
        ],
        [
          1757203200000,
          161.73
        ],
        [
          1757721600000,
          165.69
        ],
        [
          1758240000000,
          177.08
        ],
        [
          1758758400000,
          177.34
        ],
        [
          1759276800000,
          175.42
        ],
        [
          1759795200000,
          166.97
        ],
        [
          1760313600000,
          162.21
        ],
        [
          1760832000000,
          155.39
        ],
        [
          1761350400000,
          135.81
        ]
      ],
      "volumes": [
        [
          1747353600000,
          13077667.806907771
        ],
        [
          1747872000000,
          13065025.546855314
        ],
        [
          1748390400000,
          17839853.328703653
        ],
        [
          1748908800000,
          38305297.040583886
        ],
        [
          1749427200000,
          12029659.706713438
        ],
        [
          1749945600000,
          3985404.071712173
        ],
        [
          1750464000000,
          16870056.700503394
        ],
        [
          1750982400000,
          42255981.12635391
        ],
        [
          1751500800000,
          26761639.0352371
        ],
        [
          1752019200000,
          8677476.96232644
        ],
        [
          1752537600000,
          29171895.361970764
        ],
        [
          1753056000000,
          49613660.029696524
        ],
        [
          1753574400000,
          32509531.973710626
        ],
        [
          1754092800000,
          107839538.4234875
        ],
        [
          1754611200000,
          90022653.67576751
        ],
        [
          1755129600000,
          77329853.95477563
        ],
        [
          1755648000000,
          29526866.415374145
        ],
        [
          1756166400000,
          27809844.746458706
        ],
        [
          1756684800000,
          12833537.168304645
        ],
        [
          1757203200000,
          58575109.55847301
        ],
        [
          1757721600000,
          36508833.76845149
        ],
        [
          1758240000000,
          242960304.80846182
        ],
        [
          1758758400000,
          91525175.9949269
        ],
        [
          1759276800000,
          233972231.40862805
        ],
        [
          1759795200000,
          69326685.256238
        ],
        [
          1760313600000,
          150541057.37727514
        ],
        [
          1760832000000,
          69573936.15597247
        ],
        [
          1761350400000,
          54599550.98475304
        ]
      ],
      "volumes_percent_change": [
        [
          1747353600000,
          0
        ],
        [
          1747872000000,
          -0.1
        ],
        [
          1748390400000,
          36.41
        ],
        [
          1748908800000,
          192.91
        ],
        [
          1749427200000,
          -8.01
        ],
        [
          1749945600000,
          -69.53
        ],
        [
          1750464000000,
          29
        ],
        [
          1750982400000,
          223.12
        ],
        [
          1751500800000,
          104.64
        ],
        [
          1752019200000,
          -33.65
        ],
        [
          1752537600000,
          123.07
        ],
        [
          1753056000000,
          279.38
        ],
        [
          1753574400000,
          148.59
        ],
        [
          1754092800000,
          724.61
        ],
        [
          1754611200000,
          588.37
        ],
        [
          1755129600000,
          491.31
        ],
        [
          1755648000000,
          125.78
        ],
        [
          1756166400000,
          112.65
        ],
        [
          1756684800000,
          -1.87
        ],
        [
          1757203200000,
          347.9
        ],
        [
          1757721600000,
          179.17
        ],
        [
          1758240000000,
          1757.83
        ],
        [
          1758758400000,
          599.86
        ],
        [
          1759276800000,
          1689.1
        ],
        [
          1759795200000,
          430.12
        ],
        [
          1760313600000,
          1051.13
        ],
        [
          1760832000000,
          432.01
        ],
        [
          1761350400000,
          317.5
        ]
      ],
      "interval": "6_hours",
      "points": 28
    },
    "30d": {
      "prices": [
        [
          1730246400000,
          1.1140666238137549
        ],
        [
          1733356800000,
          1.1303322769256765
        ],
        [
          1736467200000,
          1.1419145678547118
        ],
        [
          1739577600000,
          1.1530823367449645
        ],
        [
          1742688000000,
          1.1605499319074197
        ],
        [
          1745798400000,
          1.1670729333966536
        ],
        [
          1748908800000,
          1.1763204094222222
        ],
        [
          1752019200000,
          1.1789545591921833
        ],
        [
          1755129600000,
          1.1871351457557482
        ],
        [
          1758240000000,
          1.198384831301199
        ]
      ],
      "prices_percent_change": [
        [
          1730246400000,
          0
        ],
        [
          1733356800000,
          1.46
        ],
        [
          1736467200000,
          2.5
        ],
        [
          1739577600000,
          3.5
        ],
        [
          1742688000000,
          4.17
        ],
        [
          1745798400000,
          4.76
        ],
        [
          1748908800000,
          5.59
        ],
        [
          1752019200000,
          5.82
        ],
        [
          1755129600000,
          6.56
        ],
        [
          1758240000000,
          7.57
        ]
      ],
      "market_caps": [
        [
          1730246400000,
          0
        ],
        [
          1733356800000,
          0
        ],
        [
          1736467200000,
          0
        ],
        [
          1739577600000,
          0
        ],
        [
          1742688000000,
          3268309006.457021
        ],
        [
          1745798400000,
          2099171446.767413
        ],
        [
          1748908800000,
          3272995732.783645
        ],
        [
          1752019200000,
          3123227434.5095267
        ],
        [
          1755129600000,
          5494879824.235885
        ],
        [
          1758240000000,
          6051292947.688032
        ]
      ],
      "market_caps_percent_change": [
        [
          1730246400000,
          0
        ],
        [
          1733356800000,
          0
        ],
        [
          1736467200000,
          0
        ],
        [
          1739577600000,
          0
        ],
        [
          1742688000000,
          0
        ],
        [
          1745798400000,
          0
        ],
        [
          1748908800000,
          0
        ],
        [
          1752019200000,
          0
        ],
        [
          1755129600000,
          0
        ],
        [
          1758240000000,
          0
        ]
      ],
      "volumes": [
        [
          1730246400000,
          13209307.194053609
        ],
        [
          1733356800000,
          46841783.91947553
        ],
        [
          1736467200000,
          43708572.25093943
        ],
        [
          1739577600000,
          20756601.07486581
        ],
        [
          1742688000000,
          4371134.998433415
        ],
        [
          1745798400000,
          5514495.527709197
        ],
        [
          1748908800000,
          38305297.040583886
        ],
        [
          1752019200000,
          8677476.96232644
        ],
        [
          1755129600000,
          77329853.95477563
        ],
        [
          1758240000000,
          242960304.80846182
        ]
      ],
      "volumes_percent_change": [
        [
          1730246400000,
          0
        ],
        [
          1733356800000,
          254.61
        ],
        [
          1736467200000,
          230.89
        ],
        [
          1739577600000,
          57.14
        ],
        [
          1742688000000,
          -66.91
        ],
        [
          1745798400000,
          -58.25
        ],
        [
          1748908800000,
          189.99
        ],
        [
          1752019200000,
          -34.31
        ],
        [
          1755129600000,
          485.42
        ],
        [
          1758240000000,
          1739.31
        ]
      ],
      "interval": "3_days",
      "points": 10
    },
    "1y": {
      "prices": [
        [
          1730246400000,
          1.1140666238137549
        ],
        [
          1732838400000,
          1.1271818748019373
        ],
        [
          1735430400000,
          1.1340594170366598
        ],
        [
          1738022400000,
          1.149913330435138
        ],
        [
          1740614400000,
          1.1515454289585936
        ],
        [
          1743206400000,
          1.1604554852328595
        ],
        [
          1745798400000,
          1.1670729333966536
        ],
        [
          1748390400000,
          1.1749740800085562
        ],
        [
          1750982400000,
          1.177426881293148
        ],
        [
          1753574400000,
          1.1858470702031463
        ],
        [
          1756166400000,
          1.1917454637113325
        ],
        [
          1758758400000,
          1.1960405818664699
        ]
      ],
      "prices_percent_change": [
        [
          1730246400000,
          0
        ],
        [
          1732838400000,
          1.18
        ],
        [
          1735430400000,
          1.79
        ],
        [
          1738022400000,
          3.22
        ],
        [
          1740614400000,
          3.36
        ],
        [
          1743206400000,
          4.16
        ],
        [
          1745798400000,
          4.76
        ],
        [
          1748390400000,
          5.47
        ],
        [
          1750982400000,
          5.69
        ],
        [
          1753574400000,
          6.44
        ],
        [
          1756166400000,
          6.97
        ],
        [
          1758758400000,
          7.36
        ]
      ],
      "market_caps": [
        [
          1730246400000,
          0
        ],
        [
          1732838400000,
          0
        ],
        [
          1735430400000,
          0
        ],
        [
          1738022400000,
          0
        ],
        [
          1740614400000,
          0
        ],
        [
          1743206400000,
          2256461407.321618
        ],
        [
          1745798400000,
          2099171446.767413
        ],
        [
          1748390400000,
          2669308293.195483
        ],
        [
          1750982400000,
          3173116563.210682
        ],
        [
          1753574400000,
          4167564154.4659424
        ],
        [
          1756166400000,
          5590729359.500165
        ],
        [
          1758758400000,
          6057065107.284272
        ]
      ],
      "market_caps_percent_change": [
        [
          1730246400000,
          0
        ],
        [
          1732838400000,
          0
        ],
        [
          1735430400000,
          0
        ],
        [
          1738022400000,
          0
        ],
        [
          1740614400000,
          0
        ],
        [
          1743206400000,
          0
        ],
        [
          1745798400000,
          0
        ],
        [
          1748390400000,
          0
        ],
        [
          1750982400000,
          0
        ],
        [
          1753574400000,
          0
        ],
        [
          1756166400000,
          0
        ],
        [
          1758758400000,
          0
        ]
      ],
      "volumes": [
        [
          1730246400000,
          13209307.194053609
        ],
        [
          1732838400000,
          21679031.04069424
        ],
        [
          1735430400000,
          21494231.04964597
        ],
        [
          1738022400000,
          33065170.65903849
        ],
        [
          1740614400000,
          11756522.257709567
        ],
        [
          1743206400000,
          28940119.75794652
        ],
        [
          1745798400000,
          5514495.527709197
        ],
        [
          1748390400000,
          17839853.328703653
        ],
        [
          1750982400000,
          42255981.12635391
        ],
        [
          1753574400000,
          32509531.973710626
        ],
        [
          1756166400000,
          27809844.746458706
        ],
        [
          1758758400000,
          91525175.9949269
        ]
      ],
      "volumes_percent_change": [
        [
          1730246400000,
          0
        ],
        [
          1732838400000,
          64.12
        ],
        [
          1735430400000,
          62.72
        ],
        [
          1738022400000,
          150.32
        ],
        [
          1740614400000,
          -11
        ],
        [
          1743206400000,
          119.09
        ],
        [
          1745798400000,
          -58.25
        ],
        [
          1748390400000,
          35.06
        ],
        [
          1750982400000,
          219.9
        ],
        [
          1753574400000,
          146.11
        ],
        [
          1756166400000,
          110.53
        ],
        [
          1758758400000,
          592.88
        ]
      ],
      "interval": "monthly",
      "points": 12
    }
  },
  "ath": 1.29,
  "atl": 1.012,
  "last_updated": "2025-10-29T10:22:50.669Z"
}