{
  "coingecko_id": "world-liberty-financial",
  "name": "World Liberty Financial",
  "symbol": "WLFI",
  "charts": {
    "7d": {
      "prices": [
        [
          1756684800000,
          0.23382691936297298
        ],
        [
          1756857600000,
          0.22776336895048277
        ],
        [
          1757030400000,
          0.18845637279219765
        ],
        [
          1757203200000,
          0.21790964833820287
        ],
        [
          1757376000000,
          0.2105771563496603
        ],
        [
          1757548800000,
          0.20232522971457384
        ],
        [
          1757721600000,
          0.20793846912180103
        ],
        [
          1757894400000,
          0.20919366682609233
        ],
        [
          1758067200000,
          0.22452887457212675
        ],
        [
          1758240000000,
          0.2198862372686527
        ],
        [
          1758412800000,
          0.22463237883156664
        ],
        [
          1758585600000,
          0.21230409459201047
        ],
        [
          1758758400000,
          0.19778877023483785
        ],
        [
          1758931200000,
          0.20997305143451395
        ],
        [
          1759104000000,
          0.22112311893456335
        ],
        [
          1759276800000,
          0.1959081371400845
        ],
        [
          1759449600000,
          0.20805297835518785
        ],
        [
          1759622400000,
          0.20065695877388715
        ],
        [
          1759795200000,
          0.1993152349574941
        ],
        [
          1759968000000,
          0.18643712654061997
        ],
        [
          1760140800000,
          0.1268170037337572
        ],
        [
          1760313600000,
          0.14090693380519398
        ],
        [
          1760486400000,
          0.14442500605597494
        ],
        [
          1760659200000,
          0.13530447587665015
        ],
        [
          1760832000000,
          0.1305340837754797
        ],
        [
          1761004800000,
          0.13196676049144032
        ],
        [
          1761177600000,
          0.12243474655501242
        ],
        [
          1761350400000,
          0.13656882010455956
        ]
      ],
      "prices_percent_change": [
        [
          1756684800000,
          0
        ],
        [
          1756857600000,
          -2.59
        ],
        [
          1757030400000,
          -19.4
        ],
        [
          1757203200000,
          -6.81
        ],
        [
          1757376000000,
          -9.94
        ],
        [
          1757548800000,
          -13.47
        ],
        [
          1757721600000,
          -11.07
        ],
        [
          1757894400000,
          -10.53
        ],
        [
          1758067200000,
          -3.98
        ],
        [
          1758240000000,
          -5.96
        ],
        [
          1758412800000,
          -3.93
        ],
        [
          1758585600000,
          -9.2
        ],
        [
          1758758400000,
          -15.41
        ],
        [
          1758931200000,
          -10.2
        ],
        [
          1759104000000,
          -5.43
        ],
        [
          1759276800000,
          -16.22
        ],
        [
          1759449600000,
          -11.02
        ],
        [
          1759622400000,
          -14.19
        ],
        [
          1759795200000,
          -14.76
        ],
        [
          1759968000000,
          -20.27
        ],
        [
          1760140800000,
          -45.76
        ],
        [
          1760313600000,
          -39.74
        ],
        [
          1760486400000,
          -38.23
        ],
        [
          1760659200000,
          -42.13
        ],
        [
          1760832000000,
          -44.17
        ],
        [
          1761004800000,
          -43.56
        ],
        [
          1761177600000,
          -47.64
        ],
        [
          1761350400000,
          -41.59
        ]
      ],
      "market_caps": [
        [
          1756684800000,
          6656403820.804826
        ],
        [
          1756857600000,
          6242912321.346511
        ],
        [
          1757030400000,
          5185086854.42622
        ],
        [
          1757203200000,
          5961347784.054906
        ],
        [
          1757376000000,
          5733253316.947378
        ],
        [
          1757548800000,
          5523804385.454971
        ],
        [
          1757721600000,
          5682346710.078059
        ],
        [
          1757894400000,
          5703926096.2140665
        ],
        [
          1758067200000,
          6106923427.078088
        ],
        [
          1758240000000,
          5997123613.848526
        ],
        [
          1758412800000,
          6122299412.095941
        ],
        [
          1758585600000,
          5802648057.086746
        ],
        [
          1758758400000,
          5377157659.276734
        ],
        [
          1758931200000,
          5699344647.783653
        ],
        [
          1759104000000,
          6026782206.104346
        ],
        [
          1759276800000,
          5331765365.506881
        ],
        [
          1759449600000,
          5648848774.269871
        ],
        [
          1759622400000,
          5485220202.050811
        ],
        [
          1759795200000,
          5445912128.063546
        ],
        [
          1759968000000,
          5095703039.34225
        ],
        [
          1760140800000,
          3497123173.0497413
        ],
        [
          1760313600000,
          3839044757.0124826
        ],
        [
          1760486400000,
          3938337395.9971595
        ],
        [
          1760659200000,
          3688036108.7164755
        ],
        [
          1760832000000,
          3556947275.1236267
        ],
        [
          1761004800000,
          3596767829.648845
        ],
        [
          1761177600000,
          3338339259.145716
        ],
        [
          1761350400000,
          3725325244.7416463
        ]
      ],
      "market_caps_percent_change": [
        [
          1756684800000,
          0
        ],
        [
          1756857600000,
          -6.21
        ],
        [
          1757030400000,
          -22.1
        ],
        [
          1757203200000,
          -10.44
        ],
        [
          1757376000000,
          -13.87
        ],
        [
          1757548800000,
          -17.02
        ],
        [
          1757721600000,
          -14.63
        ],
        [
          1757894400000,
          -14.31
        ],
        [
          1758067200000,
          -8.25
        ],
        [
          1758240000000,
          -9.9
        ],
        [
          1758412800000,
          -8.02
        ],
        [
          1758585600000,
          -12.83
        ],
        [
          1758758400000,
          -19.22
        ],
        [
          1758931200000,
          -14.38
        ],
        [
          1759104000000,
          -9.46
        ],
        [
          1759276800000,
          -19.9
        ],
        [
          1759449600000,
          -15.14
        ],
        [
          1759622400000,
          -17.59
        ],
        [
          1759795200000,
          -18.19
        ],
        [
          1759968000000,
          -23.45
        ],
        [
          1760140800000,
          -47.46
        ],
        [
          1760313600000,
          -42.33
        ],
        [
          1760486400000,
          -40.83
        ],
        [
          1760659200000,
          -44.59
        ],
        [
          1760832000000,
          -46.56
        ],
        [
          1761004800000,
          -45.97
        ],
        [
          1761177600000,
          -49.85
        ],
        [
          1761350400000,
          -44.03
        ]
      ],
      "volumes": [
        [
          1756684800000,
          2312997788.6743655
        ],
        [
          1756857600000,
          1532123186.0847077
        ],
        [
          1757030400000,
          1555936430.9035645
        ],
        [
          1757203200000,
          892038520.4669205
        ],
        [
          1757376000000,
          921993572.2305344
        ],
        [
          1757548800000,
          484104607.4134202
        ],
        [
          1757721600000,
          460247737.5016984
        ],
        [
          1757894400000,
          1018931867.2824423
        ],
        [
          1758067200000,
          428211548.21619904
        ],
        [
          1758240000000,
          291504645.9549624
        ],
        [
          1758412800000,
          463632310.83167505
        ],
        [
          1758585600000,
          881372894.1114571
        ],
        [
          1758758400000,
          383080187.4065377
        ],
        [
          1758931200000,
          473567918.7329688
        ],
        [
          1759104000000,
          451167132.65342206
        ],
        [
          1759276800000,
          329551863.8309674
        ],
        [
          1759449600000,
          272901326.60060036
        ],
        [
          1759622400000,
          147960411.3739526
        ],
        [
          1759795200000,
          176050273.67555833
        ],
        [
          1759968000000,
          351190861.47527844
        ],
        [
          1760140800000,
          890086435.7092658
        ],
        [
          1760313600000,
          431713822.34295064
        ],
        [
          1760486400000,
          349067158.9915917
        ],
        [
          1760659200000,
          218281135.4502373
        ],
        [
          1760832000000,
          85512030.77385108
        ],
        [
          1761004800000,
          124055519.30783297
        ],
        [
          1761177600000,
          162878455.55544835
        ],
        [
          1761350400000,
          198740024.0439983
        ]
      ],
      "volumes_percent_change": [
        [
          1756684800000,
          0
        ],
        [
          1756857600000,
          -33.76
        ],
        [
          1757030400000,
          -32.73
        ],
        [
          1757203200000,
          -61.43
        ],
        [
          1757376000000,
          -60.14
        ],
        [
          1757548800000,
          -79.07
        ],
        [
          1757721600000,
          -80.1
        ],
        [
          1757894400000,
          -55.95
        ],
        [
          1758067200000,
          -81.49
        ],
        [
          1758240000000,
          -87.4
        ],
        [
          1758412800000,
          -79.96
        ],
        [
          1758585600000,
          -61.89
        ],
        [
          1758758400000,
          -83.44
        ],
        [
          1758931200000,
          -79.53
        ],
        [
          1759104000000,
          -80.49
        ],
        [
          1759276800000,
          -85.75
        ],
        [
          1759449600000,
          -88.2
        ],
        [
          1759622400000,
          -93.6
        ],
        [
          1759795200000,
          -92.39
        ],
        [
          1759968000000,
          -84.82
        ],
        [
          1760140800000,
          -61.52
        ],
        [
          1760313600000,
          -81.34
        ],
        [
          1760486400000,
          -84.91
        ],
        [
          1760659200000,
          -90.56
        ],
        [
          1760832000000,
          -96.3
        ],
        [
          1761004800000,
          -94.64
        ],
        [
          1761177600000,
          -92.96
        ],
        [
          1761350400000,
          -91.41
        ]
      ],
      "interval": "6_hours",
      "points": 28
    },
    "30d": {
      "prices": [
        [
          1756684800000,
          0.23382691936297298
        ],
        [
          1757203200000,
          0.21790964833820287
        ],
        [
          1757721600000,
          0.20793846912180103
        ],
        [
          1758240000000,
          0.2198862372686527
        ],
        [
          1758758400000,
          0.19778877023483785
        ],
        [
          1759276800000,
          0.1959081371400845
        ],
        [
          1759795200000,
          0.1993152349574941
        ],
        [
          1760313600000,
          0.14090693380519398
        ],
        [
          1760832000000,
          0.1305340837754797
        ],
        [
          1761350400000,
          0.13656882010455956
        ]
      ],
      "prices_percent_change": [
        [
          1756684800000,
          0
        ],
        [
          1757203200000,
          -6.81
        ],
        [
          1757721600000,
          -11.07
        ],
        [
          1758240000000,
          -5.96
        ],
        [
          1758758400000,
          -15.41
        ],
        [
          1759276800000,
          -16.22
        ],
        [
          1759795200000,
          -14.76
        ],
        [
          1760313600000,
          -39.74
        ],
        [
          1760832000000,
          -44.17
        ],
        [
          1761350400000,
          -41.59
        ]
      ],
      "market_caps": [
        [
          1756684800000,
          6656403820.804826
        ],
        [
          1757203200000,
          5961347784.054906
        ],
        [
          1757721600000,
          5682346710.078059
        ],
        [
          1758240000000,
          5997123613.848526
        ],
        [
          1758758400000,
          5377157659.276734
        ],
        [
          1759276800000,
          5331765365.506881
        ],
        [
          1759795200000,
          5445912128.063546
        ],
        [
          1760313600000,
          3839044757.0124826
        ],
        [
          1760832000000,
          3556947275.1236267
        ],
        [
          1761350400000,
          3725325244.7416463
        ]
      ],
      "market_caps_percent_change": [
        [
          1756684800000,
          0
        ],
        [
          1757203200000,
          -10.44
        ],
        [
          1757721600000,
          -14.63
        ],
        [
          1758240000000,
          -9.9
        ],
        [
          1758758400000,
          -19.22
        ],
        [
          1759276800000,
          -19.9
        ],
        [
          1759795200000,
          -18.19
        ],
        [
          1760313600000,
          -42.33
        ],
        [
          1760832000000,
          -46.56
        ],
        [
          1761350400000,
          -44.03
        ]
      ],
      "volumes": [
        [
          1756684800000,
          2312997788.6743655
        ],
        [
          1757203200000,
          892038520.4669205
        ],
        [
          1757721600000,
          460247737.5016984
        ],
        [
          1758240000000,
          291504645.9549624
        ],
        [
          1758758400000,
          383080187.4065377
        ],
        [
          1759276800000,
          329551863.8309674
        ],
        [
          1759795200000,
          176050273.67555833
        ],
        [
          1760313600000,
          431713822.34295064
        ],
        [
          1760832000000,
          85512030.77385108
        ],
        [
          1761350400000,
          198740024.0439983
        ]
      ],
      "volumes_percent_change": [
        [
          1756684800000,
          0
        ],
        [
          1757203200000,
          -61.43
        ],
        [
          1757721600000,
          -80.1
        ],
        [
          1758240000000,
          -87.4
        ],
        [
          1758758400000,
          -83.44
        ],
        [
          1759276800000,
          -85.75
        ],
        [
          1759795200000,
          -92.39
        ],
        [
          1760313600000,
          -81.34
        ],
        [
          1760832000000,
          -96.3
        ],
        [
          1761350400000,
          -91.41
        ]
      ],
      "interval": "3_days",
      "points": 10
    },
    "1y": {
      "prices": [
        [
          1756684800000,
          0.23382691936297298
        ],
        [
          1757116800000,
          0.18159094124634853
        ],
        [
          1757548800000,
          0.20232522971457384
        ],
        [
          1757980800000,
          0.21688407851266367
        ],
        [
          1758412800000,
          0.22463237883156664
        ],
        [
          1758844800000,
          0.19169148695424568
        ],
        [
          1759276800000,
          0.1959081371400845
        ],
        [
          1759708800000,
          0.19950461275026482
        ],
        [
          1760140800000,
          0.1268170037337572
        ],
        [
          1760572800000,
          0.13857996690702848
        ],
        [
          1761004800000,
          0.13196676049144032
        ],
        [
          1761436800000,
          0.13769247607901933
        ]
      ],
      "prices_percent_change": [
        [
          1756684800000,
          0
        ],
        [
          1757116800000,
          -22.34
        ],
        [
          1757548800000,
          -13.47
        ],
        [
          1757980800000,
          -7.25
        ],
        [
          1758412800000,
          -3.93
        ],
        [
          1758844800000,
          -18.02
        ],
        [
          1759276800000,
          -16.22
        ],
        [
          1759708800000,
          -14.68
        ],
        [
          1760140800000,
          -45.76
        ],
        [
          1760572800000,
          -40.73
        ],
        [
          1761004800000,
          -43.56
        ],
        [
          1761436800000,
          -41.11
        ]
      ],
      "market_caps": [
        [
          1756684800000,
          6656403820.804826
        ],
        [
          1757116800000,
          4961992828.556703
        ],
        [
          1757548800000,
          5523804385.454971
        ],
        [
          1757980800000,
          5911360744.627681
        ],
        [
          1758412800000,
          6122299412.095941
        ],
        [
          1758844800000,
          5161164793.364755
        ],
        [
          1759276800000,
          5331765365.506881
        ],
        [
          1759708800000,
          5448793126.532446
        ],
        [
          1760140800000,
          3497123173.0497413
        ],
        [
          1760572800000,
          3775748164.937419
        ],
        [
          1761004800000,
          3596767829.648845
        ],
        [
          1761436800000,
          3755188674.640916
        ]
      ],
      "market_caps_percent_change": [
        [
          1756684800000,
          0
        ],
        [
          1757116800000,
          -25.46
        ],
        [
          1757548800000,
          -17.02
        ],
        [
          1757980800000,
          -11.19
        ],
        [
          1758412800000,
          -8.02
        ],
        [
          1758844800000,
          -22.46
        ],
        [
          1759276800000,
          -19.9
        ],
        [
          1759708800000,
          -18.14
        ],
        [
          1760140800000,
          -47.46
        ],
        [
          1760572800000,
          -43.28
        ],
        [
          1761004800000,
          -45.97
        ],
        [
          1761436800000,
          -43.59
        ]
      ],
      "volumes": [
        [
          1756684800000,
          2312997788.6743655
        ],
        [
          1757116800000,
          757224509.2376711
        ],
        [
          1757548800000,
          484104607.4134202
        ],
        [
          1757980800000,
          728297826.7549767
        ],
        [
          1758412800000,
          463632310.83167505
        ],
        [
          1758844800000,
          662226033.5536972
        ],
        [
          1759276800000,
          329551863.8309674
        ],
        [
          1759708800000,
          176875706.44542843
        ],
        [
          1760140800000,
          890086435.7092658
        ],
        [
          1760572800000,
          190002854.26425785
        ],
        [
          1761004800000,
          124055519.30783297
        ],
        [
          1761436800000,
          121481991.0382504
        ]
      ],
      "volumes_percent_change": [
        [
          1756684800000,
          0
        ],
        [
          1757116800000,
          -67.26
        ],
        [
          1757548800000,
          -79.07
        ],
        [
          1757980800000,
          -68.51
        ],
        [
          1758412800000,
          -79.96
        ],
        [
          1758844800000,
          -71.37
        ],
        [
          1759276800000,
          -85.75
        ],
        [
          1759708800000,
          -92.35
        ],
        [
          1760140800000,
          -61.52
        ],
        [
          1760572800000,
          -91.79
        ],
        [
          1761004800000,
          -94.64
        ],
        [
          1761436800000,
          -94.75
        ]
      ],
      "interval": "monthly",
      "points": 12
    }
  },
  "ath": 0.331336,
  "atl": 0.104606,
  "last_updated": "2025-10-29T10:23:21.093Z"
}