{
  "coingecko_id": "wrapped-bitcoin",
  "name": "Wrapped Bitcoin",
  "symbol": "WBTC",
  "charts": {
    "7d": {
      "prices": [
        [
          1747440000000,
          103475.37377523552
        ],
        [
          1747958400000,
          111202.73646736733
        ],
        [
          1748476800000,
          107806.88471857918
        ],
        [
          1748995200000,
          105369.70889887188
        ],
        [
          1749513600000,
          110054.259484131
        ],
        [
          1750032000000,
          105441.49480725655
        ],
        [
          1750550400000,
          101414.44124840596
        ],
        [
          1751068800000,
          106985.36394562377
        ],
        [
          1751587200000,
          109555.79353294383
        ],
        [
          1752105600000,
          111326.11343116153
        ],
        [
          1752624000000,
          117535.29717743416
        ],
        [
          1753142400000,
          117402.645086908
        ],
        [
          1753660800000,
          119440.72684148606
        ],
        [
          1754179200000,
          112513.21618668617
        ],
        [
          1754697600000,
          116661.40349976257
        ],
        [
          1755216000000,
          118471.9873383171
        ],
        [
          1755734400000,
          114212.67480701827
        ],
        [
          1756252800000,
          111881.9342633622
        ],
        [
          1756771200000,
          108986.06807712278
        ],
        [
          1757289600000,
          111092.63731941556
        ],
        [
          1757808000000,
          116077.6679153634
        ],
        [
          1758326400000,
          115539.37162177617
        ],
        [
          1758844800000,
          109169.27976570243
        ],
        [
          1759363200000,
          118280.8992901909
        ],
        [
          1759881600000,
          121543.47984453352
        ],
        [
          1760400000000,
          115140.2690388128
        ],
        [
          1760918400000,
          108773.88839057166
        ],
        [
          1761436800000,
          111393.10810992392
        ]
      ],
      "prices_percent_change": [
        [
          1747440000000,
          0
        ],
        [
          1747958400000,
          7.47
        ],
        [
          1748476800000,
          4.19
        ],
        [
          1748995200000,
          1.83
        ],
        [
          1749513600000,
          6.36
        ],
        [
          1750032000000,
          1.9
        ],
        [
          1750550400000,
          -1.99
        ],
        [
          1751068800000,
          3.39
        ],
        [
          1751587200000,
          5.88
        ],
        [
          1752105600000,
          7.59
        ],
        [
          1752624000000,
          13.59
        ],
        [
          1753142400000,
          13.46
        ],
        [
          1753660800000,
          15.43
        ],
        [
          1754179200000,
          8.73
        ],
        [
          1754697600000,
          12.74
        ],
        [
          1755216000000,
          14.49
        ],
        [
          1755734400000,
          10.38
        ],
        [
          1756252800000,
          8.12
        ],
        [
          1756771200000,
          5.33
        ],
        [
          1757289600000,
          7.36
        ],
        [
          1757808000000,
          12.18
        ],
        [
          1758326400000,
          11.66
        ],
        [
          1758844800000,
          5.5
        ],
        [
          1759363200000,
          14.31
        ],
        [
          1759881600000,
          17.46
        ],
        [
          1760400000000,
          11.27
        ],
        [
          1760918400000,
          5.12
        ],
        [
          1761436800000,
          7.65
        ]
      ],
      "market_caps": [
        [
          1747440000000,
          13329742774.593174
        ],
        [
          1747958400000,
          14320387093.444927
        ],
        [
          1748476800000,
          13876815661.837557
        ],
        [
          1748995200000,
          13575984070.864985
        ],
        [
          1749513600000,
          14179134008.940613
        ],
        [
          1750032000000,
          13587792650.754213
        ],
        [
          1750550400000,
          13035761560.201624
        ],
        [
          1751068800000,
          13784003338.681318
        ],
        [
          1751587200000,
          14112623998.214584
        ],
        [
          1752105600000,
          14343055785.579056
        ],
        [
          1752624000000,
          15157158026.472223
        ],
        [
          1753142400000,
          15129364747.134834
        ],
        [
          1753660800000,
          15390044999.538595
        ],
        [
          1754179200000,
          14254174648.622633
        ],
        [
          1754697600000,
          14798406660.59133
        ],
        [
          1755216000000,
          15052845242.629696
        ],
        [
          1755734400000,
          14523908148.77719
        ],
        [
          1756252800000,
          14223015156.715528
        ],
        [
          1756771200000,
          13873788555.630882
        ],
        [
          1757289600000,
          14145477108.113844
        ],
        [
          1757808000000,
          14764274455.941074
        ],
        [
          1758326400000,
          14699109281.712126
        ],
        [
          1758844800000,
          13881950445.901672
        ],
        [
          1759363200000,
          15021100012.13538
        ],
        [
          1759881600000,
          15440827338.02708
        ],
        [
          1760400000000,
          14615833359.104631
        ],
        [
          1760918400000,
          13786606233.376623
        ],
        [
          1761436800000,
          14124108509.065292
        ]
      ],
      "market_caps_percent_change": [
        [
          1747440000000,
          0
        ],
        [
          1747958400000,
          7.43
        ],
        [
          1748476800000,
          4.1
        ],
        [
          1748995200000,
          1.85
        ],
        [
          1749513600000,
          6.37
        ],
        [
          1750032000000,
          1.94
        ],
        [
          1750550400000,
          -2.21
        ],
        [
          1751068800000,
          3.41
        ],
        [
          1751587200000,
          5.87
        ],
        [
          1752105600000,
          7.6
        ],
        [
          1752624000000,
          13.71
        ],
        [
          1753142400000,
          13.5
        ],
        [
          1753660800000,
          15.46
        ],
        [
          1754179200000,
          6.94
        ],
        [
          1754697600000,
          11.02
        ],
        [
          1755216000000,
          12.93
        ],
        [
          1755734400000,
          8.96
        ],
        [
          1756252800000,
          6.7
        ],
        [
          1756771200000,
          4.08
        ],
        [
          1757289600000,
          6.12
        ],
        [
          1757808000000,
          10.76
        ],
        [
          1758326400000,
          10.27
        ],
        [
          1758844800000,
          4.14
        ],
        [
          1759363200000,
          12.69
        ],
        [
          1759881600000,
          15.84
        ],
        [
          1760400000000,
          9.65
        ],
        [
          1760918400000,
          3.43
        ],
        [
          1761436800000,
          5.96
        ]
      ],
      "volumes": [
        [
          1747440000000,
          252619187.0859732
        ],
        [
          1747958400000,
          437874964.18910336
        ],
        [
          1748476800000,
          200869967.06759048
        ],
        [
          1748995200000,
          208800928.1769618
        ],
        [
          1749513600000,
          278296654.55754644
        ],
        [
          1750032000000,
          95603509.3166593
        ],
        [
          1750550400000,
          206814086.7450241
        ],
        [
          1751068800000,
          153216511.62122115
        ],
        [
          1751587200000,
          255511688.35829353
        ],
        [
          1752105600000,
          264238973.40765503
        ],
        [
          1752624000000,
          356955769.51778865
        ],
        [
          1753142400000,
          285527662.7603771
        ],
        [
          1753660800000,
          122838337.1702372
        ],
        [
          1754179200000,
          187325186.5430789
        ],
        [
          1754697600000,
          148318897.04742134
        ],
        [
          1755216000000,
          496129903.14163655
        ],
        [
          1755734400000,
          263573715.01365733
        ],
        [
          1756252800000,
          419034122.86679846
        ],
        [
          1756771200000,
          323516121.4994464
        ],
        [
          1757289600000,
          84240743.17124312
        ],
        [
          1757808000000,
          150353270.59397295
        ],
        [
          1758326400000,
          150782357.71485496
        ],
        [
          1758844800000,
          425766741.59721684
        ],
        [
          1759363200000,
          301078445.42512274
        ],
        [
          1759881600000,
          367140223.66446996
        ],
        [
          1760400000000,
          463076891.756294
        ],
        [
          1760918400000,
          459615059.599748
        ],
        [
          1761436800000,
          92981031.96817787
        ]
      ],
      "volumes_percent_change": [
        [
          1747440000000,
          0
        ],
        [
          1747958400000,
          73.33
        ],
        [
          1748476800000,
          -20.49
        ],
        [
          1748995200000,
          -17.35
        ],
        [
          1749513600000,
          10.16
        ],
        [
          1750032000000,
          -62.16
        ],
        [
          1750550400000,
          -18.13
        ],
        [
          1751068800000,
          -39.35
        ],
        [
          1751587200000,
          1.15
        ],
        [
          1752105600000,
          4.6
        ],
        [
          1752624000000,
          41.3
        ],
        [
          1753142400000,
          13.03
        ],
        [
          1753660800000,
          -51.37
        ],
        [
          1754179200000,
          -25.85
        ],
        [
          1754697600000,
          -41.29
        ],
        [
          1755216000000,
          96.39
        ],
        [
          1755734400000,
          4.34
        ],
        [
          1756252800000,
          65.88
        ],
        [
          1756771200000,
          28.06
        ],
        [
          1757289600000,
          -66.65
        ],
        [
          1757808000000,
          -40.48
        ],
        [
          1758326400000,
          -40.31
        ],
        [
          1758844800000,
          68.54
        ],
        [
          1759363200000,
          19.18
        ],
        [
          1759881600000,
          45.33
        ],
        [
          1760400000000,
          83.31
        ],
        [
          1760918400000,
          81.94
        ],
        [
          1761436800000,
          -63.19
        ]
      ],
      "interval": "6_hours",
      "points": 28
    },
    "30d": {
      "prices": [
        [
          1730332800000,
          72300.60616074956
        ],
        [
          1733443200000,
          96705.99608580154
        ],
        [
          1736553600000,
          94648.03308626874
        ],
        [
          1739664000000,
          97301.03393242958
        ],
        [
          1742774400000,
          85692.97204139724
        ],
        [
          1745884800000,
          94905.224833607
        ],
        [
          1748995200000,
          105369.70889887188
        ],
        [
          1752105600000,
          111326.11343116153
        ],
        [
          1755216000000,
          118471.9873383171
        ],
        [
          1758326400000,
          115539.37162177617
        ]
      ],
      "prices_percent_change": [
        [
          1730332800000,
          0
        ],
        [
          1733443200000,
          33.76
        ],
        [
          1736553600000,
          30.91
        ],
        [
          1739664000000,
          34.58
        ],
        [
          1742774400000,
          18.52
        ],
        [
          1745884800000,
          31.26
        ],
        [
          1748995200000,
          45.74
        ],
        [
          1752105600000,
          53.98
        ],
        [
          1755216000000,
          63.86
        ],
        [
          1758326400000,
          59.8
        ]
      ],
      "market_caps": [
        [
          1730332800000,
          10613284062.141796
        ],
        [
          1733443200000,
          13285640207.685524
        ],
        [
          1736553600000,
          12478856717.754297
        ],
        [
          1739664000000,
          12561300058.891878
        ],
        [
          1742774400000,
          11052779803.57146
        ],
        [
          1745884800000,
          12228532082.217491
        ],
        [
          1748995200000,
          13575984070.864985
        ],
        [
          1752105600000,
          14343055785.579056
        ],
        [
          1755216000000,
          15052845242.629696
        ],
        [
          1758326400000,
          14699109281.712126
        ]
      ],
      "market_caps_percent_change": [
        [
          1730332800000,
          0
        ],
        [
          1733443200000,
          25.18
        ],
        [
          1736553600000,
          17.58
        ],
        [
          1739664000000,
          18.35
        ],
        [
          1742774400000,
          4.14
        ],
        [
          1745884800000,
          15.22
        ],
        [
          1748995200000,
          27.92
        ],
        [
          1752105600000,
          35.14
        ],
        [
          1755216000000,
          41.83
        ],
        [
          1758326400000,
          38.5
        ]
      ],
      "volumes": [
        [
          1730332800000,
          261945631.82122025
        ],
        [
          1733443200000,
          1063935644.8445419
        ],
        [
          1736553600000,
          369753413.3085537
        ],
        [
          1739664000000,
          100787073.75491384
        ],
        [
          1742774400000,
          90659181.18596268
        ],
        [
          1745884800000,
          245810204.9455144
        ],
        [
          1748995200000,
          208800928.1769618
        ],
        [
          1752105600000,
          264238973.40765503
        ],
        [
          1755216000000,
          496129903.14163655
        ],
        [
          1758326400000,
          150782357.71485496
        ]
      ],
      "volumes_percent_change": [
        [
          1730332800000,
          0
        ],
        [
          1733443200000,
          306.17
        ],
        [
          1736553600000,
          41.16
        ],
        [
          1739664000000,
          -61.52
        ],
        [
          1742774400000,
          -65.39
        ],
        [
          1745884800000,
          -6.16
        ],
        [
          1748995200000,
          -20.29
        ],
        [
          1752105600000,
          0.88
        ],
        [
          1755216000000,
          89.4
        ],
        [
          1758326400000,
          -42.44
        ]
      ],
      "interval": "3_days",
      "points": 10
    },
    "1y": {
      "prices": [
        [
          1730332800000,
          72300.60616074956
        ],
        [
          1732924800000,
          97208.17744873563
        ],
        [
          1735516800000,
          93856.93431265517
        ],
        [
          1738108800000,
          101051.39817731557
        ],
        [
          1740700800000,
          84578.52955594631
        ],
        [
          1743292800000,
          82498.0379498523
        ],
        [
          1745884800000,
          94905.224833607
        ],
        [
          1748476800000,
          107806.88471857918
        ],
        [
          1751068800000,
          106985.36394562377
        ],
        [
          1753660800000,
          119440.72684148606
        ],
        [
          1756252800000,
          111881.9342633622
        ],
        [
          1758844800000,
          109169.27976570243
        ]
      ],
      "prices_percent_change": [
        [
          1730332800000,
          0
        ],
        [
          1732924800000,
          34.45
        ],
        [
          1735516800000,
          29.81
        ],
        [
          1738108800000,
          39.77
        ],
        [
          1740700800000,
          16.98
        ],
        [
          1743292800000,
          14.1
        ],
        [
          1745884800000,
          31.26
        ],
        [
          1748476800000,
          49.11
        ],
        [
          1751068800000,
          47.97
        ],
        [
          1753660800000,
          65.2
        ],
        [
          1756252800000,
          54.75
        ],
        [
          1758844800000,
          50.99
        ]
      ],
      "market_caps": [
        [
          1730332800000,
          10613284062.141796
        ],
        [
          1732924800000,
          13627384723.835262
        ],
        [
          1735516800000,
          12451617111.554483
        ],
        [
          1738108800000,
          13045728068.993557
        ],
        [
          1740700800000,
          10922354207.079569
        ],
        [
          1743292800000,
          10627278828.009596
        ],
        [
          1745884800000,
          12228532082.217491
        ],
        [
          1748476800000,
          13876815661.837557
        ],
        [
          1751068800000,
          13784003338.681318
        ],
        [
          1753660800000,
          15390044999.538595
        ],
        [
          1756252800000,
          14223015156.715528
        ],
        [
          1758844800000,
          13881950445.901672
        ]
      ],
      "market_caps_percent_change": [
        [
          1730332800000,
          0
        ],
        [
          1732924800000,
          28.4
        ],
        [
          1735516800000,
          17.32
        ],
        [
          1738108800000,
          22.92
        ],
        [
          1740700800000,
          2.91
        ],
        [
          1743292800000,
          0.13
        ],
        [
          1745884800000,
          15.22
        ],
        [
          1748476800000,
          30.75
        ],
        [
          1751068800000,
          29.88
        ],
        [
          1753660800000,
          45.01
        ],
        [
          1756252800000,
          34.01
        ],
        [
          1758844800000,
          30.8
        ]
      ],
      "volumes": [
        [
          1730332800000,
          261945631.82122025
        ],
        [
          1732924800000,
          353687519.33013195
        ],
        [
          1735516800000,
          226837108.04869518
        ],
        [
          1738108800000,
          515522551.9377396
        ],
        [
          1740700800000,
          452755228.3101529
        ],
        [
          1743292800000,
          134982157.04800677
        ],
        [
          1745884800000,
          245810204.9455144
        ],
        [
          1748476800000,
          200869967.06759048
        ],
        [
          1751068800000,
          153216511.62122115
        ],
        [
          1753660800000,
          122838337.1702372
        ],
        [
          1756252800000,
          419034122.86679846
        ],
        [
          1758844800000,
          425766741.59721684
        ]
      ],
      "volumes_percent_change": [
        [
          1730332800000,
          0
        ],
        [
          1732924800000,
          35.02
        ],
        [
          1735516800000,
          -13.4
        ],
        [
          1738108800000,
          96.81
        ],
        [
          1740700800000,
          72.84
        ],
        [
          1743292800000,
          -48.47
        ],
        [
          1745884800000,
          -6.16
        ],
        [
          1748476800000,
          -23.32
        ],
        [
          1751068800000,
          -41.51
        ],
        [
          1753660800000,
          -53.11
        ],
        [
          1756252800000,
          59.97
        ],
        [
          1758844800000,
          62.54
        ]
      ],
      "interval": "monthly",
      "points": 12
    }
  },
  "ath": 125932,
  "atl": 3139.17,
  "last_updated": "2025-10-30T03:12:16.805Z"
}